[
    {
        "key": "dbln",
        "value": "%7B%2261578321413055%22%3A%22KVhRroNS%22%2C%2261579423868614%22%3A%22gcKIzOPq%22%2C%2261566305175486%22%3A%223DDEMkrJ%22%2C%2261557180704764%22%3A%22og1P6OWI%22%7D",
        "domain": "facebook.com",
        "path": "/login/device-based/",
        "hostOnly": false,
        "creation": "2025-09-18T07:39:06.321Z",
        "lastAccessed": "2025-09-18T07:39:06.321Z"
    },
    {
        "key": "datr",
        "value": "iOjBaKIeaEI6K90PkCICg_oB",
        "domain": "facebook.com",
        "path": "/",
        "hostOnly": false,
        "creation": "2025-09-18T07:39:06.321Z",
        "lastAccessed": "2025-09-18T07:39:06.321Z"
    },
    {
        "key": "sb",
        "value": "iOjBaOq3VzPKhgYBxQbVYxhr",
        "domain": "facebook.com",
        "path": "/",
        "hostOnly": false,
        "creation": "2025-09-18T07:39:06.321Z",
        "lastAccessed": "2025-09-18T07:39:06.321Z"
    },
    {
        "key": "ps_l",
        "value": "1",
        "domain": "facebook.com",
        "path": "/",
        "hostOnly": false,
        "creation": "2025-09-18T07:39:06.321Z",
        "lastAccessed": "2025-09-18T07:39:06.321Z"
    },
    {
        "key": "ps_n",
        "value": "1",
        "domain": "facebook.com",
        "path": "/",
        "hostOnly": false,
        "creation": "2025-09-18T07:39:06.321Z",
        "lastAccessed": "2025-09-18T07:39:06.321Z"
    },
    {
        "key": "vpd",
        "value": "v1%3B716x377x3.25",
        "domain": "facebook.com",
        "path": "/",
        "hostOnly": false,
        "creation": "2025-09-18T07:39:06.321Z",
        "lastAccessed": "2025-09-18T07:39:06.321Z"
    },
    {
        "key": "m_pixel_ratio",
        "value": "3.25",
        "domain": "facebook.com",
        "path": "/",
        "hostOnly": false,
        "creation": "2025-09-18T07:39:06.321Z",
        "lastAccessed": "2025-09-18T07:39:06.321Z"
    },
    {
        "key": "wd",
        "value": "377x831",
        "domain": "facebook.com",
        "path": "/",
        "hostOnly": false,
        "creation": "2025-09-18T07:39:06.321Z",
        "lastAccessed": "2025-09-18T07:39:06.321Z"
    },
    {
        "key": "c_user",
        "value": "61580955274484",
        "domain": "facebook.com",
        "path": "/",
        "hostOnly": false,
        "creation": "2025-09-18T07:39:06.321Z",
        "lastAccessed": "2025-09-18T07:39:06.321Z"
    },
    {
        "key": "xs",
        "value": "36%3AUu6Cv-3QQdnE3w%3A2%3A1758181113%3A-1%3A-1",
        "domain": "facebook.com",
        "path": "/",
        "hostOnly": false,
        "creation": "2025-09-18T07:39:06.321Z",
        "lastAccessed": "2025-09-18T07:39:06.321Z"
    },
    {
        "key": "fr",
        "value": "00Gn5o2HgoxVvffkT.AWdEDOheBvacSpytMXJKBjtoTueLC6dETN6tzX7LuIQOUidFyWc.BoweiI..AAA.0.0.Boy7b-.AWdTkA_sd94kcBpZckJoNTdVmD4",
        "domain": "facebook.com",
        "path": "/",
        "hostOnly": false,
        "creation": "2025-09-18T07:39:06.321Z",
        "lastAccessed": "2025-09-18T07:39:06.321Z"
    },
    {
        "key": "locale",
        "value": "en_GB",
        "domain": "facebook.com",
        "path": "/",
        "hostOnly": false,
        "creation": "2025-09-18T07:39:06.321Z",
        "lastAccessed": "2025-09-18T07:39:06.321Z"
    },
    {
        "key": "pas",
        "value": "61578321413055%3ANZPa4YbHEG%2C61566305175486%3ARquE8ZCLse%2C61579423868614%3AMg7mOKC8yh%2C61557180704764%3AEmebQo16yG%2C61580955274484%3AsuvAmVSXlR",
        "domain": "facebook.com",
        "path": "/",
        "hostOnly": false,
        "creation": "2025-09-18T07:39:06.321Z",
        "lastAccessed": "2025-09-18T07:39:06.321Z"
    },
    {
        "key": "fbl_st",
        "value": "101723383%3BT%3A29303018",
        "domain": "facebook.com",
        "path": "/",
        "hostOnly": false,
        "creation": "2025-09-18T07:39:06.321Z",
        "lastAccessed": "2025-09-18T07:39:06.321Z"
    },
    {
        "key": "wl_cbv",
        "value": "v2%3Bclient_version%3A2926%3Btimestamp%3A1758181118%3BCRCM%3A-2082348551",
        "domain": "facebook.com",
        "path": "/",
        "hostOnly": false,
        "creation": "2025-09-18T07:39:06.321Z",
        "lastAccessed": "2025-09-18T07:39:06.321Z"
    }
]
